sigcalc/__init__.py
sigcalc/constants.py
sigcalc/quantity.py
sigcalc/test_constants.py
sigcalc/test_quantity.py
sigcalc/test_quantity_hypothesis.py
sigcalc-0.2.0.dist-info/LICENSE.rst
sigcalc-0.2.0.dist-info/METADATA
sigcalc-0.2.0.dist-info/WHEEL
sigcalc-0.2.0.dist-info/RECORD
