Metadata-Version: 2.1
Name: sigcalc
Version: 0.2.0
Summary: significant figures calculations
Home-page: https://github.com/jeremyagray/sigcalc
License: GPL-3.0-or-later
Author: Jeremy A Gray
Author-email: gray@flyquackswim.com
Maintainer: Jeremy A Gray
Maintainer-email: gray@flyquackswim.com
Requires-Python: >=3.10.1,<4.0
Classifier: Development Status :: 2 - Pre-Alpha
Classifier: Intended Audience :: Developers
Classifier: Intended Audience :: Science/Research
Classifier: License :: OSI Approved :: GNU General Public License v3 or later (GPLv3+)
Classifier: Programming Language :: Python :: 3
Classifier: Programming Language :: Python :: 3.11
Classifier: Programming Language :: Python :: 3.12
Classifier: Programming Language :: Python :: 3.10
Requires-Dist: mpmath (>=1,<2)
Project-URL: Documentation, https://sigcalc.readthedocs.io/
Project-URL: Issues, https://github.com/jeremyagray/sigcalc/issues
Project-URL: Repository, https://github.com/jeremyagray/sigcalc
